jinplate/__init__.py
jinplate/__version__.py
jinplate/cli.py
jinplate/plugins/__init__.py
jinplate/plugins/loader.py
jinplate/plugins/filetype/__init__.py
jinplate/plugins/filetype/base.py
jinplate/plugins/filetype/dotenv.py
jinplate/plugins/filetype/json.py
jinplate/plugins/filetype/yaml.py
jinplate/plugins/scheme/__init__.py
jinplate/plugins/scheme/base.py
jinplate/plugins/scheme/file.py
jinplate/plugins/scheme/http.py
jinplate-0.0.7.dist-info/LICENSE.txt
jinplate-0.0.7.dist-info/METADATA
jinplate-0.0.7.dist-info/WHEEL
jinplate-0.0.7.dist-info/entry_points.txt
jinplate-0.0.7.dist-info/top_level.txt
jinplate-0.0.7.dist-info/RECORD
