Metadata-Version: 2.1
Name: jinplate
Version: 0.0.7
Summary: CLI renderer for Jinja2
Author: Evin Dunn
License: MIT License
Project-URL: homepage, https://github.com/evindunn/jinplate
Classifier: Environment :: Console
Classifier: Intended Audience :: Developers
Classifier: Intended Audience :: Information Technology
Classifier: Intended Audience :: System Administrators
Classifier: Programming Language :: Python :: 3
Classifier: License :: OSI Approved :: MIT License
Classifier: Framework :: Ansible
Classifier: Topic :: System :: Systems Administration
Classifier: Topic :: Utilities
Classifier: Topic :: Text Processing
Requires-Python: >=3.10
License-File: LICENSE.txt
Requires-Dist: click ~=8.1.7
Requires-Dist: Jinja2 ~=3.1.4
Requires-Dist: python-dotenv ~=1.0.1
Requires-Dist: PyYAML ~=6.0.1
Provides-Extra: ansible
Requires-Dist: ansible-core >=2.9 ; extra == 'ansible'
